LiveCap/__init__.py
LiveCap/capture.py
LiveCap/desktop.py
LiveCap/Capture/__init__.py
LiveCap/Capture/DXGI/DXGICapture.dll
LiveCap/Capture/DXGI/DXGICapture.py
LiveCap/Capture/DXGI/__init__.py
LiveCap/Capture/GDI/GDICapture.dll
LiveCap/Capture/GDI/GDICapure.py
LiveCap/Capture/GDI/__init__.py
LiveCap/Capture/WGC/__init__.py
LiveCap/Capture/WGC/screenshot.py
LiveCap/Capture/WGC/test.py
LiveCap/Capture/WGC/utils.py
LiveCap/Stream/__init__.py
LiveCap/Stream/stream.py
LiveCap/Stream/utils.py
LiveCap-0.4.0.dist-info/METADATA
LiveCap-0.4.0.dist-info/WHEEL
LiveCap-0.4.0.dist-info/top_level.txt
LiveCap-0.4.0.dist-info/RECORD
